flake8_useless_assert/__init__.py
flake8_useless_assert/flake_diagnostic.py
flake8_useless_assert/patch_const.py
flake8_useless_assert/plugin.py
flake8_useless_assert/rules.py
flake8_useless_assert-0.4.2.dist-info/entry_points.txt
flake8_useless_assert-0.4.2.dist-info/LICENSE
flake8_useless_assert-0.4.2.dist-info/WHEEL
flake8_useless_assert-0.4.2.dist-info/METADATA
flake8_useless_assert-0.4.2.dist-info/RECORD
