Metadata-Version: 2.1
Name: flake8-useless-assert
Version: 0.4.2
Summary: flake8 plugin to catch useless `assert` statements
Home-page: https://github.com/decorator-factory/flake8-useless-assert
License: MIT
Author: decorator-factory
Author-email: decorator-factory@yandex.ru
Requires-Python: >=3.7,<4.0
Classifier: License :: OSI Approved :: MIT License
Classifier: Programming Language :: Python :: 3
Classifier: Programming Language :: Python :: 3.7
Classifier: Programming Language :: Python :: 3.8
Classifier: Programming Language :: Python :: 3.9
Requires-Dist: flake8 (>=3.9,<5.0)
Project-URL: Repository, https://github.com/decorator-factory/flake8-useless-assert
